{
      "attachment": {
        "type": "template",
        "payload": {
          "template_type": "button",
          "text": "Lựa chọn của bạn?",
          "buttons":[
          {
            "type": "postback",
            "title": "Chỉnh sửa bot",
            "payload": "custom"
          },
          {
            "type": "web_url",
            "url": "http://www.dynamic-memory.com",
            "title": "DMS Software"
          },
          {
            "type": "postback",
            "title": "Home",
            "payload": "home"
          }
           ]
        }
      }
    }
